desarte/__init__.py
desarte/event.py
desarte/model.py
desarte/process.py
desarte/simulation.py
desarte/simulator.py
desarte-0.1.1.dist-info/METADATA
desarte-0.1.1.dist-info/WHEEL
desarte-0.1.1.dist-info/top_level.txt
desarte-0.1.1.dist-info/RECORD
