Metadata-Version: 2.1
Name: desarte
Version: 0.1.1
Summary: Simulador de eventos discretos.
Home-page: https://github.com/BigData95/pip_simulator
Author: Dr Ricado Marcelin Jimenez
License: UNKNOWN
Keywords: discrete-event,event simulador,distribuido
Platform: UNKNOWN
